pypack/__init__.py
pypack/gui/__init__.py
pypack/gui/button.py
pypack/gui/start.py
pypack/gui/table.py
pypack/gui/window.py
OlPack-0.1.3.dist-info/LICENSE
OlPack-0.1.3.dist-info/METADATA
OlPack-0.1.3.dist-info/WHEEL
OlPack-0.1.3.dist-info/top_level.txt
OlPack-0.1.3.dist-info/RECORD
