Metadata-Version: 2.1
Name: OlPack
Version: 0.1.3
Summary: A collection of tools to simplify your Python experience!
Home-page: https://github.com/Ollieq1977336/PyPack
Author: Ollie Quayle
Author-email: Olliequayle08@icloud.com
Classifier: Programming Language :: Python :: 3
Classifier: Programming Language :: Python :: 3.6
Classifier: Programming Language :: Python :: 3.7
Classifier: Programming Language :: Python :: 3.8
Classifier: Programming Language :: Python :: 3.9
Classifier: Programming Language :: Python :: 3.10
Classifier: Programming Language :: Python :: 3.11
Classifier: License :: OSI Approved :: MIT License
Classifier: Operating System :: OS Independent
Requires-Python: >=3.6
License-File: LICENSE
Provides-Extra: dev
Requires-Dist: twine >=4.0.2 ; extra == 'dev'
